{
  "$schema": "http://json-schema.org/draft-07/schema#",
  "type": "object",
  "properties": {
    "id": {
      "type": "integer"
    },
    "created_at": {
      "type": "string",
      "format": "date-time"
    },
    "updated_at": {
      "type": "string",
      "format": "date-time"
    },
    "recipient_email_address": {
      "type": ["null", "string"]
    },
    "status": {
      "type": ["null", "string"]
    },
    "bounced": {
      "type": ["null", "boolean"]
    },
    "send_after": {
      "type": ["null", "string"],
      "format": "date-time"
    },
    "sent_at": {
      "type": ["null", "string"],
      "format": "date-time"
    },
    "view_tracking": {
      "type": ["null", "boolean"]
    },
    "click_tracking": {
      "type": ["null", "boolean"]
    },
    "personalization": {
      "type": ["null", "string"]
    },
    "counts": {
      "type": ["null", "object"],
      "additionalProperties": false,
      "properties": {
        "clicks": {
          "type": ["null", "integer"]
        },

        "views": {
          "type": ["null", "integer"]
        },
        "replies": {
          "type": ["null", "integer"]
        },

        "unique_devices": {
          "type": ["null", "integer"]
        },

        "unique_locations": {
          "type": ["null", "integer"]
        },

        "attachments": {
          "type": ["null", "integer"]
        }
      }
    },
    "headers": {
      "type": ["null", "object"],
      "additionalProperties": false,
      "properties": {
        "In-Reply-To": {
          "type": ["null", "string"]
        },

        "References": {
          "type": ["null", "string"]
        },
        "to": {
          "type": ["null", "string"]
        },

        "cc": {
          "type": ["null", "string"]
        },

        "in_reply_to": {
          "type": ["null", "string"]
        },

        "bcc": {
          "type": ["null", "string"]
        }
      }
    },
    "user": {
      "type": ["null", "object"],
      "additionalProperties": false,
      "properties": {
        "_href": {
          "type": ["null", "string"]
        },
        "id": {
          "type": ["null", "integer"]
        }
      }
    },
    "recipient": {
      "type": ["null", "object"],
      "additionalProperties": false,
      "properties": {
        "_href": {
          "type": ["null", "string"]
        },
        "id": {
          "type": ["null", "integer"]
        }
      }
    },
    "mailing": {
      "type": ["null", "object"],
      "additionalProperties": false,
      "properties": {
        "id": {
          "type": ["null", "integer"]
        }
      }
    },
    "action": {
      "type": ["null", "object"],
      "additionalProperties": false,
      "properties": {
        "id": {
          "type": ["null", "integer"]
        }
      }
    },
    "crm_activity": {
      "type": ["null", "object"],
      "additionalProperties": false,
      "properties": {
        "_href": {
          "type": ["null", "string"]
        },
        "id": {
          "type": ["null", "integer"]
        }
      }
    },
    "cadence": {
      "type": ["null", "object"],
      "additionalProperties": false,
      "properties": {
        "_href": {
          "type": ["null", "string"]
        },
        "id": {
          "type": ["null", "integer"]
        }
      }
    },
    "step": {
      "type": ["null", "object"],
      "additionalProperties": false,
      "properties": {
        "_href": {
          "type": ["null", "string"]
        },
        "id": {
          "type": ["null", "integer"]
        }
      }
    },
    "email_template": {
      "type": ["null", "object"],
      "additionalProperties": false,
      "properties": {
        "_href": {
          "type": ["null", "string"]
        },
        "id": {
          "type": ["null", "integer"]
        }
      }
    }
  }
}
