{
  "$schema": "https://json-schema.org/draft-07/schema#",
  "type": "object",
  "properties": {
    "date": {
      "description": "The date when the annotation was made",
      "type": ["null", "string"],
      "format": "date"
    },
    "details": {
      "description": "Additional details or information related to the annotation",
      "type": ["null", "string"]
    },
    "id": {
      "description": "The unique identifier for the annotation",
      "type": ["null", "integer"]
    },
    "label": {
      "description": "The label assigned to the annotation",
      "type": ["null", "string"]
    }
  }
}
